{"namedChunkGroups":{"polyfill":{"name":"polyfill","assets":[{"name":"webpack-runtime-982d27382b34e7d8a139.js","size":5048},{"name":"polyfill-e7fd2f565a857dc57935.js","size":82650}],"filteredAssets":0,"assetsSize":87698,"filteredAuxiliaryAssets":2,"auxiliaryAssetsSize":221671},"app":{"name":"app","assets":[{"name":"webpack-runtime-982d27382b34e7d8a139.js","size":5048},{"name":"styles.a8a6c4bc127163f3e5cf.css","size":150465},{"name":"framework-89ddeb149991009fa125.js","size":128977},{"name":"app-045aaaf2fd75b140ebc9.js","size":89545}],"filteredAssets":0,"assetsSize":374035,"filteredAuxiliaryAssets":3,"auxiliaryAssetsSize":768189},"component---src-pages-404-tsx":{"name":"component---src-pages-404-tsx","assets":[{"name":"styles.a8a6c4bc127163f3e5cf.css","size":150465},{"name":"commons-d713a2e885391163ebc0.js","size":39589},{"name":"component---src-pages-404-tsx-e7f7c5f2dc54bc1dd260.js","size":486}],"filteredAssets":0,"assetsSize":190540,"filteredAuxiliaryAssets":2,"auxiliaryAssetsSize":138563},"component---src-pages-index-tsx":{"name":"component---src-pages-index-tsx","assets":[{"name":"styles.a8a6c4bc127163f3e5cf.css","size":150465},{"name":"commons-d713a2e885391163ebc0.js","size":39589},{"name":"component---src-pages-index-tsx-754b928430f77f73fe9e.js","size":791}],"filteredAssets":0,"assetsSize":190845,"filteredAuxiliaryAssets":2,"auxiliaryAssetsSize":139183}},"assetsByChunkName":{"polyfill":["webpack-runtime-982d27382b34e7d8a139.js","polyfill-e7fd2f565a857dc57935.js"],"app":["webpack-runtime-982d27382b34e7d8a139.js","styles.a8a6c4bc127163f3e5cf.css","framework-89ddeb149991009fa125.js","app-045aaaf2fd75b140ebc9.js"],"component---src-pages-404-tsx":["styles.a8a6c4bc127163f3e5cf.css","commons-d713a2e885391163ebc0.js","component---src-pages-404-tsx-e7f7c5f2dc54bc1dd260.js"],"component---src-pages-index-tsx":["styles.a8a6c4bc127163f3e5cf.css","commons-d713a2e885391163ebc0.js","component---src-pages-index-tsx-754b928430f77f73fe9e.js"]},"childAssetsByChunkName":{}}